labs/chap7/src/inner_product_4x16.v
// 4x16-bit inner product unit.
//
// Verilog/SystemVerilog 语法速记：
// - module ... endmodule：定义一个硬件模块，相当于一个可复用的电路块。
// - input/output：模块端口方向。input 是外部输入，output 是模块输出。
// - wire：连线类型，通常由组合逻辑或其他模块驱动。
// - reg：寄存器类型，可在 always 时序块里保存值；这里的 result 会被触发器保存。
// - signed [15:0]：16 位有符号数，[15] 是符号位，[0] 是最低位。
// - activations [0:3]：unpacked array，表示 4 个 16 位元素。
module inner_product_4x16 (
    input wire clk,                             // 时钟信号；posedge clk 表示上升沿触发
    input wire reset,                           // 同步复位；为 1 时在下一个时钟上升沿清零
    input wire enable,                          // 计算使能；为 1 时锁存输入并更新结果
    input wire signed [15:0] activations [0:3], // 4 个输入激活值，每个 16 位有符号
    input wire signed [15:0] weights [0:3],     // 4 个权重值，每个 16 位有符号
    output reg signed [31:0] result             // 内积结果；16x16 乘法再求和，用 32 位保存
);
    // 输入寄存器。
    // 这里先把外部输入保存到寄存器中，再用寄存器值参与组合乘加。
    // 这样做的硬件含义是：输入在时钟边沿被采样，后续组合逻辑看到的是稳定值。
    reg signed [15:0] activations_reg [0:3];
    reg signed [15:0] weights_reg [0:3];
    
    // 组合逻辑部分。
    // wire 不能在 always 时序块中赋值；这里用连续赋值 assign 的简写形式：
    //     wire name = expression;
    // dot_product 会随 activations_reg/weights_reg 的变化自动重新计算。
    wire signed [31:0] dot_product = 
        (activations_reg[0] * weights_reg[0]) +
        (activations_reg[1] * weights_reg[1]) +
        (activations_reg[2] * weights_reg[2]) +
        (activations_reg[3] * weights_reg[3]);
    
    // 寄存器更新逻辑。
    // always @(posedge clk)：描述时序逻辑，综合后通常是触发器。
    // <= 是非阻塞赋值，时序逻辑里常用它，含义是所有左值在同一个时钟边沿一起更新。
    integer i;
    always @(posedge clk) begin
        if (reset) begin
            // for 循环在硬件描述中表示“生成重复赋值逻辑”，不是运行时的软件循环。
            // 这里把 4 个寄存器元素全部清零。
            for (i = 0; i < 4; i = i + 1) begin
                activations_reg[i] <= 16'd0;
                weights_reg[i] <= 16'd0;
            end
            result <= 32'd0;
        end else if (enable) begin
            // enable 有效时采样新的输入。
            for (i = 0; i < 4; i = i + 1) begin
                activations_reg[i] <= activations[i];
                weights_reg[i] <= weights[i];
            end
            // 注意：因为上面是非阻塞赋值，result 本拍拿到的是“旧寄存器值”的 dot_product。
            // 测试平台保持 enable 多个时钟周期，所以第二个有效时钟边沿会得到新输入的内积结果。
            result <= dot_product;
        end
    end
endmodule

labs/chap7/src/matrix_vector_mult_4x4x16.v
// 4x4 matrix-vector multiplier.
//
// 本模块计算一个 1x4 行向量 activations 乘以一个 4x4 矩阵 weights：
//
//     results[j] = activations[0] * weights[0][j]
//                + activations[1] * weights[1][j]
//                + activations[2] * weights[2][j]
//                + activations[3] * weights[3][j]
//
// 也就是说，每个输出 results[j] 都是 activations 和 weights 的第 j 列做内积。
module matrix_vector_mult_4x4x16 (
    input wire clk,                                  // 所有子模块共用同一个时钟
    input wire reset,                                // 所有子模块共用同步复位
    input wire enable,                               // 所有子模块共用计算使能
    input wire signed [15:0] activations [0:3],      // 1x4 输入行向量
    input wire signed [15:0] weights [0:3][0:3],     // 4x4 权重矩阵，weights[row][column]
    output wire signed [31:0] results [0:3]          // 1x4 输出行向量
);

    // inner_product_4x16 的 weights 端口需要一个 4 元向量。
    // 但矩阵按 weights[row][column] 存储，所以第 j 个输出要取第 j 列：
    //     weights[0][j], weights[1][j], weights[2][j], weights[3][j]
    //
    // 下面 4 个 weight_col* 是“列向量连线”。
    // assign 是连续赋值，表示这些 wire 始终等于右侧表达式，不需要时钟。
    wire signed [15:0] weight_col0 [0:3];
    wire signed [15:0] weight_col1 [0:3];
    wire signed [15:0] weight_col2 [0:3];
    wire signed [15:0] weight_col3 [0:3];

    assign weight_col0[0] = weights[0][0];
    assign weight_col0[1] = weights[1][0];
    assign weight_col0[2] = weights[2][0];
    assign weight_col0[3] = weights[3][0];

    assign weight_col1[0] = weights[0][1];
    assign weight_col1[1] = weights[1][1];
    assign weight_col1[2] = weights[2][1];
    assign weight_col1[3] = weights[3][1];

    assign weight_col2[0] = weights[0][2];
    assign weight_col2[1] = weights[1][2];
    assign weight_col2[2] = weights[2][2];
    assign weight_col2[3] = weights[3][2];

    assign weight_col3[0] = weights[0][3];
    assign weight_col3[1] = weights[1][3];
    assign weight_col3[2] = weights[2][3];
    assign weight_col3[3] = weights[3][3];

    // 模块实例化语法：
    //     module_name instance_name ( .port_name(signal_name), ... );
    //
    // .clk(clk) 的意思是：把当前模块里的 clk 信号连接到子模块的 clk 端口。
    // 这里实例化 4 个内积单元，分别计算输出向量的 4 个元素。
    inner_product_4x16 ipu0 (
        .clk(clk),
        .reset(reset),
        .enable(enable),
        .activations(activations), // 所有输出都使用同一个输入向量
        .weights(weight_col0),     // 第 0 列权重
        .result(results[0])        // results[0] = activations dot weights column 0
    );

    inner_product_4x16 ipu1 (
        .clk(clk),
        .reset(reset),
        .enable(enable),
        .activations(activations),
        .weights(weight_col1),
        .result(results[1])
    );

    inner_product_4x16 ipu2 (
        .clk(clk),
        .reset(reset),
        .enable(enable),
        .activations(activations),
        .weights(weight_col2),
        .result(results[2])
    );

    inner_product_4x16 ipu3 (
        .clk(clk),
        .reset(reset),
        .enable(enable),
        .activations(activations),
        .weights(weight_col3),
        .result(results[3])
    );

endmodule

labs/chap7/sim/wave_matrix_vector.vcd
$version Generated by VerilatedVcd $end
$timescale 1ps $end
 $scope module TOP $end
  $var wire 1 9! clk $end
  $var wire 1 :! reset $end
  $var wire 1 ;! enable $end
  $var wire 16 <! activations[0] [15:0] $end
  $var wire 16 =! activations[1] [15:0] $end
  $var wire 16 >! activations[2] [15:0] $end
  $var wire 16 ?! activations[3] [15:0] $end
  $var wire 16 @! weights[0][0] [15:0] $end
  $var wire 16 A! weights[0][1] [15:0] $end
  $var wire 16 B! weights[0][2] [15:0] $end
  $var wire 16 C! weights[0][3] [15:0] $end
  $var wire 16 D! weights[1][0] [15:0] $end
  $var wire 16 E! weights[1][1] [15:0] $end
  $var wire 16 F! weights[1][2] [15:0] $end
  $var wire 16 G! weights[1][3] [15:0] $end
  $var wire 16 H! weights[2][0] [15:0] $end
  $var wire 16 I! weights[2][1] [15:0] $end
  $var wire 16 J! weights[2][2] [15:0] $end
  $var wire 16 K! weights[2][3] [15:0] $end
  $var wire 16 L! weights[3][0] [15:0] $end
  $var wire 16 M! weights[3][1] [15:0] $end
  $var wire 16 N! weights[3][2] [15:0] $end
  $var wire 16 O! weights[3][3] [15:0] $end
  $var wire 32 P! results[0] [31:0] $end
  $var wire 32 Q! results[1] [31:0] $end
  $var wire 32 R! results[2] [31:0] $end
  $var wire 32 S! results[3] [31:0] $end
  $scope module matrix_vector_mult_4x4x16 $end
   $var wire 1 9! clk $end
   $var wire 1 :! reset $end
   $var wire 1 ;! enable $end
   $var wire 16 # activations[0] [15:0] $end
   $var wire 16 $ activations[1] [15:0] $end
   $var wire 16 % activations[2] [15:0] $end
   $var wire 16 & activations[3] [15:0] $end
   $var wire 16 ' weights[0][0] [15:0] $end
   $var wire 16 ( weights[0][1] [15:0] $end
   $var wire 16 ) weights[0][2] [15:0] $end
   $var wire 16 * weights[0][3] [15:0] $end
   $var wire 16 + weights[1][0] [15:0] $end
   $var wire 16 , weights[1][1] [15:0] $end
   $var wire 16 - weights[1][2] [15:0] $end
   $var wire 16 . weights[1][3] [15:0] $end
   $var wire 16 / weights[2][0] [15:0] $end
   $var wire 16 0 weights[2][1] [15:0] $end
   $var wire 16 1 weights[2][2] [15:0] $end
   $var wire 16 2 weights[2][3] [15:0] $end
   $var wire 16 3 weights[3][0] [15:0] $end
   $var wire 16 4 weights[3][1] [15:0] $end
   $var wire 16 5 weights[3][2] [15:0] $end
   $var wire 16 6 weights[3][3] [15:0] $end
   $var wire 32 g results[0] [31:0] $end
   $var wire 32 h results[1] [31:0] $end
   $var wire 32 i results[2] [31:0] $end
   $var wire 32 j results[3] [31:0] $end
   $var wire 16 7 weight_col0[0] [15:0] $end
   $var wire 16 8 weight_col0[1] [15:0] $end
   $var wire 16 9 weight_col0[2] [15:0] $end
   $var wire 16 : weight_col0[3] [15:0] $end
   $var wire 16 ; weight_col1[0] [15:0] $end
   $var wire 16 < weight_col1[1] [15:0] $end
   $var wire 16 = weight_col1[2] [15:0] $end
   $var wire 16 > weight_col1[3] [15:0] $end
   $var wire 16 ? weight_col2[0] [15:0] $end
   $var wire 16 @ weight_col2[1] [15:0] $end
   $var wire 16 A weight_col2[2] [15:0] $end
   $var wire 16 B weight_col2[3] [15:0] $end
   $var wire 16 C weight_col3[0] [15:0] $end
   $var wire 16 D weight_col3[1] [15:0] $end
   $var wire 16 E weight_col3[2] [15:0] $end
   $var wire 16 F weight_col3[3] [15:0] $end
   $scope module ipu0 $end
    $var wire 1 9! clk $end
    $var wire 1 :! reset $end
    $var wire 1 ;! enable $end
    $var wire 16 G activations[0] [15:0] $end
    $var wire 16 H activations[1] [15:0] $end
    $var wire 16 I activations[2] [15:0] $end
    $var wire 16 J activations[3] [15:0] $end
    $var wire 16 K weights[0] [15:0] $end
    $var wire 16 L weights[1] [15:0] $end
    $var wire 16 M weights[2] [15:0] $end
    $var wire 16 N weights[3] [15:0] $end
    $var wire 32 k result [31:0] $end
    $var wire 16 l activations_reg[0] [15:0] $end
    $var wire 16 m activations_reg[1] [15:0] $end
    $var wire 16 n activations_reg[2] [15:0] $end
    $var wire 16 o activations_reg[3] [15:0] $end
    $var wire 16 p weights_reg[0] [15:0] $end
    $var wire 16 q weights_reg[1] [15:0] $end
    $var wire 16 r weights_reg[2] [15:0] $end
    $var wire 16 s weights_reg[3] [15:0] $end
    $var wire 32 t dot_product [31:0] $end
    $var wire 32 u i [31:0] $end
   $upscope $end
   $scope module ipu1 $end
    $var wire 1 9! clk $end
    $var wire 1 :! reset $end
    $var wire 1 ;! enable $end
    $var wire 16 O activations[0] [15:0] $end
    $var wire 16 P activations[1] [15:0] $end
    $var wire 16 Q activations[2] [15:0] $end
    $var wire 16 R activations[3] [15:0] $end
    $var wire 16 S weights[0] [15:0] $end
    $var wire 16 T weights[1] [15:0] $end
    $var wire 16 U weights[2] [15:0] $end
    $var wire 16 V weights[3] [15:0] $end
    $var wire 32 v result [31:0] $end
    $var wire 16 w activations_reg[0] [15:0] $end
    $var wire 16 x activations_reg[1] [15:0] $end
    $var wire 16 y activations_reg[2] [15:0] $end
    $var wire 16 z activations_reg[3] [15:0] $end
    $var wire 16 { weights_reg[0] [15:0] $end
    $var wire 16 | weights_reg[1] [15:0] $end
    $var wire 16 } weights_reg[2] [15:0] $end
    $var wire 16 ~ weights_reg[3] [15:0] $end
    $var wire 32 !! dot_product [31:0] $end
    $var wire 32 "! i [31:0] $end
   $upscope $end
   $scope module ipu2 $end
    $var wire 1 9! clk $end
    $var wire 1 :! reset $end
    $var wire 1 ;! enable $end
    $var wire 16 W activations[0] [15:0] $end
    $var wire 16 X activations[1] [15:0] $end
    $var wire 16 Y activations[2] [15:0] $end
    $var wire 16 Z activations[3] [15:0] $end
    $var wire 16 [ weights[0] [15:0] $end
    $var wire 16 \ weights[1] [15:0] $end
    $var wire 16 ] weights[2] [15:0] $end
    $var wire 16 ^ weights[3] [15:0] $end
    $var wire 32 #! result [31:0] $end
    $var wire 16 $! activations_reg[0] [15:0] $end
    $var wire 16 %! activations_reg[1] [15:0] $end
    $var wire 16 &! activations_reg[2] [15:0] $end
    $var wire 16 '! activations_reg[3] [15:0] $end
    $var wire 16 (! weights_reg[0] [15:0] $end
    $var wire 16 )! weights_reg[1] [15:0] $end
    $var wire 16 *! weights_reg[2] [15:0] $end
    $var wire 16 +! weights_reg[3] [15:0] $end
    $var wire 32 ,! dot_product [31:0] $end
    $var wire 32 -! i [31:0] $end
   $upscope $end
   $scope module ipu3 $end
    $var wire 1 9! clk $end
    $var wire 1 :! reset $end
    $var wire 1 ;! enable $end
    $var wire 16 _ activations[0] [15:0] $end
    $var wire 16 ` activations[1] [15:0] $end
    $var wire 16 a activations[2] [15:0] $end
    $var wire 16 b activations[3] [15:0] $end
    $var wire 16 c weights[0] [15:0] $end
    $var wire 16 d weights[1] [15:0] $end
    $var wire 16 e weights[2] [15:0] $end
    $var wire 16 f weights[3] [15:0] $end
    $var wire 32 .! result [31:0] $end
    $var wire 16 /! activations_reg[0] [15:0] $end
    $var wire 16 0! activations_reg[1] [15:0] $end
    $var wire 16 1! activations_reg[2] [15:0] $end
    $var wire 16 2! activations_reg[3] [15:0] $end
    $var wire 16 3! weights_reg[0] [15:0] $end
    $var wire 16 4! weights_reg[1] [15:0] $end
    $var wire 16 5! weights_reg[2] [15:0] $end
    $var wire 16 6! weights_reg[3] [15:0] $end
    $var wire 32 7! dot_product [31:0] $end
    $var wire 32 8! i [31:0] $end
   $upscope $end
  $upscope $end
 $upscope $end
$enddefinitions $end


#0
b0000000000000000 #
b0000000000000000 $
b0000000000000000 %
b0000000000000000 &
b0000000000000000 '
b0000000000000000 (
b0000000000000000 )
b0000000000000000 *
b0000000000000000 +
b0000000000000000 ,
b0000000000000000 -
b0000000000000000 .
b0000000000000000 /
b0000000000000000 0
b0000000000000000 1
b0000000000000000 2
b0000000000000000 3
b0000000000000000 4
b0000000000000000 5
b0000000000000000 6
b0000000000000000 7
b0000000000000000 8
b0000000000000000 9
b0000000000000000 :
b0000000000000000 ;
b0000000000000000 <
b0000000000000000 =
b0000000000000000 >
b0000000000000000 ?
b0000000000000000 @
b0000000000000000 A
b0000000000000000 B
b0000000000000000 C
b0000000000000000 D
b0000000000000000 E
b0000000000000000 F
b0000000000000000 G
b0000000000000000 H
b0000000000000000 I
b0000000000000000 J
b0000000000000000 K
b0000000000000000 L
b0000000000000000 M
b0000000000000000 N
b0000000000000000 O
b0000000000000000 P
b0000000000000000 Q
b0000000000000000 R
b0000000000000000 S
b0000000000000000 T
b0000000000000000 U
b0000000000000000 V
b0000000000000000 W
b0000000000000000 X
b0000000000000000 Y
b0000000000000000 Z
b0000000000000000 [
b0000000000000000 \
b0000000000000000 ]
b0000000000000000 ^
b0000000000000000 _
b0000000000000000 `
b0000000000000000 a
b0000000000000000 b
b0000000000000000 c
b0000000000000000 d
b0000000000000000 e
b0000000000000000 f
b00000000000000000000000000000000 g
b00000000000000000000000000000000 h
b00000000000000000000000000000000 i
b00000000000000000000000000000000 j
b00000000000000000000000000000000 k
b0000000000000000 l
b0000000000000000 m
b0000000000000000 n
b0000000000000000 o
b0000000000000000 p
b0000000000000000 q
b0000000000000000 r
b0000000000000000 s
b00000000000000000000000000000000 t
b00000000000000000000000000000000 u
b00000000000000000000000000000000 v
b0000000000000000 w
b0000000000000000 x
b0000000000000000 y
b0000000000000000 z
b0000000000000000 {
b0000000000000000 |
b0000000000000000 }
b0000000000000000 ~
b00000000000000000000000000000000 !!
b00000000000000000000000000000000 "!
b00000000000000000000000000000000 #!
b0000000000000000 $!
b0000000000000000 %!
b0000000000000000 &!
b0000000000000000 '!
b0000000000000000 (!
b0000000000000000 )!
b0000000000000000 *!
b0000000000000000 +!
b00000000000000000000000000000000 ,!
b00000000000000000000000000000000 -!
b00000000000000000000000000000000 .!
b0000000000000000 /!
b0000000000000000 0!
b0000000000000000 1!
b0000000000000000 2!
b0000000000000000 3!
b0000000000000000 4!
b0000000000000000 5!
b0000000000000000 6!
b00000000000000000000000000000000 7!
b00000000000000000000000000000000 8!
19!
1:!
0;!
b0000000000000000 <!
b0000000000000000 =!
b0000000000000000 >!
b0000000000000000 ?!
b0000000000000000 @!
b0000000000000000 A!
b0000000000000000 B!
b0000000000000000 C!
b0000000000000000 D!
b0000000000000000 E!
b0000000000000000 F!
b0000000000000000 G!
b0000000000000000 H!
b0000000000000000 I!
b0000000000000000 J!
b0000000000000000 K!
b0000000000000000 L!
b0000000000000000 M!
b0000000000000000 N!
b0000000000000000 O!
b00000000000000000000000000000000 P!
b00000000000000000000000000000000 Q!
b00000000000000000000000000000000 R!
b00000000000000000000000000000000 S!
#1
09!
#2
b00000000000000000000000000000100 u
b00000000000000000000000000000100 "!
b00000000000000000000000000000100 -!
b00000000000000000000000000000100 8!
19!
#3
09!
#4
19!
#5
09!
0:!
#6
19!
#7
09!
#8
19!
#9
b0000000000000001 #
b0000000000000010 $
b0000000000000011 %
b0000000000000100 &
b0000000000000001 '
b0000000000000001 ,
b0000000000000001 1
b0000000000000001 6
b0000000000000001 7
b0000000000000001 <
b0000000000000001 A
b0000000000000001 F
b0000000000000001 G
b0000000000000010 H
b0000000000000011 I
b0000000000000100 J
b0000000000000001 K
b0000000000000001 O
b0000000000000010 P
b0000000000000011 Q
b0000000000000100 R
b0000000000000001 T
b0000000000000001 W
b0000000000000010 X
b0000000000000011 Y
b0000000000000100 Z
b0000000000000001 ]
b0000000000000001 _
b0000000000000010 `
b0000000000000011 a
b0000000000000100 b
b0000000000000001 f
09!
b0000000000000001 <!
b0000000000000010 =!
b0000000000000011 >!
b0000000000000100 ?!
b0000000000000001 @!
b0000000000000001 E!
b0000000000000001 J!
b0000000000000001 O!
#10
19!
#11
09!
1;!
#12
b0000000000000001 l
b0000000000000010 m
b0000000000000011 n
b0000000000000100 o
b0000000000000001 p
b00000000000000000000000000000001 t
b0000000000000001 w
b0000000000000010 x
b0000000000000011 y
b0000000000000100 z
b0000000000000001 |
b00000000000000000000000000000010 !!
b0000000000000001 $!
b0000000000000010 %!
b0000000000000011 &!
b0000000000000100 '!
b0000000000000001 *!
b00000000000000000000000000000011 ,!
b0000000000000001 /!
b0000000000000010 0!
b0000000000000011 1!
b0000000000000100 2!
b0000000000000001 6!
b00000000000000000000000000000100 7!
19!
#13
09!
#14
b00000000000000000000000000000001 g
b00000000000000000000000000000010 h
b00000000000000000000000000000011 i
b00000000000000000000000000000100 j
b00000000000000000000000000000001 k
b00000000000000000000000000000010 v
b00000000000000000000000000000011 #!
b00000000000000000000000000000100 .!
19!
b00000000000000000000000000000001 P!
b00000000000000000000000000000010 Q!
b00000000000000000000000000000011 R!
b00000000000000000000000000000100 S!
#15
09!
#16
19!
#17
09!
#18
19!
#19
09!
0;!
