labs/chap7/src/inner_product_4x16.v
// 4x16-bit inner product unit.
//
// Verilog/SystemVerilog 语法速记：
// - module ... endmodule：定义一个硬件模块，相当于一个可复用的电路块。
// - input/output：模块端口方向。input 是外部输入，output 是模块输出。
// - wire：连线类型，通常由组合逻辑或其他模块驱动。
// - reg：寄存器类型，可在 always 时序块里保存值；这里的 result 会被触发器保存。
// - signed [15:0]：16 位有符号数，[15] 是符号位，[0] 是最低位。
// - activations [0:3]：unpacked array，表示 4 个 16 位元素。
module inner_product_4x16 (
    input wire clk,                             // 时钟信号；posedge clk 表示上升沿触发
    input wire reset,                           // 同步复位；为 1 时在下一个时钟上升沿清零
    input wire enable,                          // 计算使能；为 1 时锁存输入并更新结果
    input wire signed [15:0] activations [0:3], // 4 个输入激活值，每个 16 位有符号
    input wire signed [15:0] weights [0:3],     // 4 个权重值，每个 16 位有符号
    output reg signed [31:0] result             // 内积结果；16x16 乘法再求和，用 32 位保存
);
    // 输入寄存器。
    // 这里先把外部输入保存到寄存器中，再用寄存器值参与组合乘加。
    // 这样做的硬件含义是：输入在时钟边沿被采样，后续组合逻辑看到的是稳定值。
    reg signed [15:0] activations_reg [0:3];
    reg signed [15:0] weights_reg [0:3];
    
    // 组合逻辑部分。
    // wire 不能在 always 时序块中赋值；这里用连续赋值 assign 的简写形式：
    //     wire name = expression;
    // dot_product 会随 activations_reg/weights_reg 的变化自动重新计算。
    wire signed [31:0] dot_product = 
        (activations_reg[0] * weights_reg[0]) +
        (activations_reg[1] * weights_reg[1]) +
        (activations_reg[2] * weights_reg[2]) +
        (activations_reg[3] * weights_reg[3]);
    
    // 寄存器更新逻辑。
    // always @(posedge clk)：描述时序逻辑，综合后通常是触发器。
    // <= 是非阻塞赋值，时序逻辑里常用它，含义是所有左值在同一个时钟边沿一起更新。
    integer i;
    always @(posedge clk) begin
        if (reset) begin
            // for 循环在硬件描述中表示“生成重复赋值逻辑”，不是运行时的软件循环。
            // 这里把 4 个寄存器元素全部清零。
            for (i = 0; i < 4; i = i + 1) begin
                activations_reg[i] <= 16'd0;
                weights_reg[i] <= 16'd0;
            end
            result <= 32'd0;
        end else if (enable) begin
            // enable 有效时采样新的输入。
            for (i = 0; i < 4; i = i + 1) begin
                activations_reg[i] <= activations[i];
                weights_reg[i] <= weights[i];
            end
            // 注意：因为上面是非阻塞赋值，result 本拍拿到的是“旧寄存器值”的 dot_product。
            // 测试平台保持 enable 多个时钟周期，所以第二个有效时钟边沿会得到新输入的内积结果。
            result <= dot_product;
        end
    end
endmodule

labs/chap7/sim/wave_inner.vcd
$version Generated by VerilatedVcd $end
$timescale 1ps $end
 $scope module TOP $end
  $var wire 1 5 clk $end
  $var wire 1 6 reset $end
  $var wire 1 7 enable $end
  $var wire 16 8 activations[0] [15:0] $end
  $var wire 16 9 activations[1] [15:0] $end
  $var wire 16 : activations[2] [15:0] $end
  $var wire 16 ; activations[3] [15:0] $end
  $var wire 16 < weights[0] [15:0] $end
  $var wire 16 = weights[1] [15:0] $end
  $var wire 16 > weights[2] [15:0] $end
  $var wire 16 ? weights[3] [15:0] $end
  $var wire 32 @ result [31:0] $end
  $scope module inner_product_4x16 $end
   $var wire 1 5 clk $end
   $var wire 1 6 reset $end
   $var wire 1 7 enable $end
   $var wire 16 # activations[0] [15:0] $end
   $var wire 16 $ activations[1] [15:0] $end
   $var wire 16 % activations[2] [15:0] $end
   $var wire 16 & activations[3] [15:0] $end
   $var wire 16 ' weights[0] [15:0] $end
   $var wire 16 ( weights[1] [15:0] $end
   $var wire 16 ) weights[2] [15:0] $end
   $var wire 16 * weights[3] [15:0] $end
   $var wire 32 @ result [31:0] $end
   $var wire 16 + activations_reg[0] [15:0] $end
   $var wire 16 , activations_reg[1] [15:0] $end
   $var wire 16 - activations_reg[2] [15:0] $end
   $var wire 16 . activations_reg[3] [15:0] $end
   $var wire 16 / weights_reg[0] [15:0] $end
   $var wire 16 0 weights_reg[1] [15:0] $end
   $var wire 16 1 weights_reg[2] [15:0] $end
   $var wire 16 2 weights_reg[3] [15:0] $end
   $var wire 32 3 dot_product [31:0] $end
   $var wire 32 4 i [31:0] $end
  $upscope $end
 $upscope $end
$enddefinitions $end


#0
b0000000000000000 #
b0000000000000000 $
b0000000000000000 %
b0000000000000000 &
b0000000000000000 '
b0000000000000000 (
b0000000000000000 )
b0000000000000000 *
b0000000000000000 +
b0000000000000000 ,
b0000000000000000 -
b0000000000000000 .
b0000000000000000 /
b0000000000000000 0
b0000000000000000 1
b0000000000000000 2
b00000000000000000000000000000000 3
b00000000000000000000000000000000 4
15
16
07
b0000000000000000 8
b0000000000000000 9
b0000000000000000 :
b0000000000000000 ;
b0000000000000000 <
b0000000000000000 =
b0000000000000000 >
b0000000000000000 ?
b00000000000000000000000000000000 @
#1
05
#2
b00000000000000000000000000000100 4
15
#3
05
#4
15
#5
05
06
#6
15
#7
05
#8
15
#9
b0000000000000001 #
b0000000000000010 $
b0000000000000011 %
b0000000000000100 &
b0000000000000001 '
b0000000000000010 (
b0000000000000011 )
b0000000000000100 *
05
b0000000000000001 8
b0000000000000010 9
b0000000000000011 :
b0000000000000100 ;
b0000000000000001 <
b0000000000000010 =
b0000000000000011 >
b0000000000000100 ?
#10
15
#11
05
17
#12
b0000000000000001 +
b0000000000000010 ,
b0000000000000011 -
b0000000000000100 .
b0000000000000001 /
b0000000000000010 0
b0000000000000011 1
b0000000000000100 2
b00000000000000000000000000011110 3
15
#13
05
#14
15
b00000000000000000000000000011110 @
#15
05
07
